hyperpopy/__init__.py
hyperpopy/analytic_utils.py
hyperpopy/generation_utils.py
hyperpopy/mc_utils.py
hyperpopy/pylint_mc.txt
hyperpopy-0.1.3.dist-info/licenses/LICENSE
hyperpopy-0.1.3.dist-info/METADATA
hyperpopy-0.1.3.dist-info/WHEEL
hyperpopy-0.1.3.dist-info/top_level.txt
hyperpopy-0.1.3.dist-info/RECORD
