Metadata-Version: 2.4
Name: hyperpopy
Version: 0.1.3
Summary: Poisson Hyperplane Model Package
Author-email: Alec Shelley <ams01@stanford.edu>
Maintainer-email: Alec Shelley <ams01@stanford.edu>
License-Expression: MIT
Project-URL: Homepage, https://github.com/AlecShelley/hyperpopy
Project-URL: Repository, https://github.com/AlecShelley/hyperpopy
Project-URL: Issues, https://github.com/AlecShelley/hyperpopy/issues
Keywords: poisson,hyperplane,geometry,probability,monte-carlo
Classifier: Development Status :: 3 - Alpha
Classifier: Intended Audience :: Science/Research
Classifier: Operating System :: OS Independent
Classifier: Programming Language :: Python :: 3
Classifier: Programming Language :: Python :: 3.8
Classifier: Programming Language :: Python :: 3.9
Classifier: Programming Language :: Python :: 3.10
Classifier: Programming Language :: Python :: 3.11
Classifier: Programming Language :: Python :: 3.12
Classifier: Topic :: Scientific/Engineering :: Mathematics
Classifier: Topic :: Scientific/Engineering :: Physics
Requires-Python: >=3.8
License-File: LICENSE
Requires-Dist: numpy>=1.20.0
Requires-Dist: scipy>=1.7.0
Requires-Dist: matplotlib>=3.3.0
Requires-Dist: scikit-learn>=1.0.0
Requires-Dist: numba>=0.50.0
Provides-Extra: dev
Requires-Dist: pytest>=6.0; extra == "dev"
Requires-Dist: pytest-cov>=2.0; extra == "dev"
Requires-Dist: black>=21.0; extra == "dev"
Requires-Dist: isort>=5.0; extra == "dev"
Requires-Dist: pylint>=2.8.0; extra == "dev"
Requires-Dist: mypy>=0.800; extra == "dev"
Requires-Dist: jupyter>=1.0; extra == "dev"
Requires-Dist: ipykernel>=6.0; extra == "dev"
Provides-Extra: docs
Requires-Dist: sphinx>=4.0; extra == "docs"
Requires-Dist: sphinx-rtd-theme>=1.0; extra == "docs"
Requires-Dist: nbsphinx>=0.8; extra == "docs"
Dynamic: license-file
